ctool/__init__.py
ctool-0.0.1.dist-info/LICENSE
ctool-0.0.1.dist-info/METADATA
ctool-0.0.1.dist-info/WHEEL
ctool-0.0.1.dist-info/entry_points.txt
ctool-0.0.1.dist-info/top_level.txt
ctool-0.0.1.dist-info/RECORD
